_version.py
rgpycrumbs/__init__.py
rgpycrumbs/_aux.py
rgpycrumbs/cli.py
rgpycrumbs/eon/__init__.py
rgpycrumbs/eon/con_splitter.py
rgpycrumbs/eon/generate_nwchem_input.py
rgpycrumbs/eon/plt_neb.py
rgpycrumbs/eon/ptmdisp.py
rgpycrumbs/func/__init__.py
rgpycrumbs/func/muller_brown.py
rgpycrumbs/geom/__init__.py
rgpycrumbs/geom/detect_fragments.py
rgpycrumbs/parsers/__init__.py
rgpycrumbs/parsers/bless.py
rgpycrumbs/parsers/common.py
rgpycrumbs/plumed/__init__.py
rgpycrumbs/plumed/direct_reconstruction.py
rgpycrumbs/prefix/__init__.py
rgpycrumbs/prefix/delete_packages.py
rgpycrumbs/search/helpers.py
rgpycrumbs/time/helpers.py
rgpycrumbs/xts/__init__.py
rgpycrumbs/xts/cuh2/__init__.py
rgpycrumbs/xts/cuh2/datgen.py
rgpycrumbs/xts/saddle/__init__.py
rgpycrumbs/xts/saddle/cuh2.py
rgpycrumbs/xts/saddle/mb.py
tests/conftest.py
tests/test_detect_fragments.py
tests/test_importer.py
tests/test_ptmdisp.py
rgpycrumbs-0.0.6.dist-info/METADATA
rgpycrumbs-0.0.6.dist-info/WHEEL
rgpycrumbs-0.0.6.dist-info/licenses/LICENSE
rgpycrumbs-0.0.6.dist-info/RECORD
