Metadata-Version: 2.4
Name: rgpycrumbs
Version: 0.0.6
Summary: A dispatcher-based analytical and visualization suite for chemical physics
Project-URL: Documentation, https://github.com/HaoZeke/rgpycrumbs#readme
Project-URL: Issues, https://github.com/HaoZeke/rgpycrumbs/issues
Project-URL: Source, https://github.com/HaoZeke/rgpycrumbs
Author-email: Rohit Goswami <rgoswami@ieee.org>
License: MIT
License-File: LICENSE
Keywords: analysis,parsers,plots
Classifier: Development Status :: 4 - Beta
Classifier: Programming Language :: Python
Classifier: Programming Language :: Python :: 3 :: Only
Classifier: Programming Language :: Python :: 3.9
Classifier: Programming Language :: Python :: 3.10
Classifier: Programming Language :: Python :: 3.11
Classifier: Programming Language :: Python :: 3.12
Classifier: Programming Language :: Python :: Implementation :: CPython
Requires-Python: >=3.10
